<annotation>
	<folder>orignal-images</folder>
	<filename>img494.png</filename>
	<path>/Users/zhongjie/MyWorkspace/temp/orignal-images/img494.png</path>
	<source>
		<database>Unknown</database>
	</source>
	<size>
		<width>630</width>
		<height>805</height>
		<depth>3</depth>
	</size>
	<segmented>0</segmented>
	<object>
		<name>table</name>
		<pose>Unspecified</pose>
		<truncated>0</truncated>
		<difficult>0</difficult>
		<bndbox>
			<xmin>432</xmin>
			<ymin>122</ymin>
			<xmax>491</xmax>
			<ymax>410</ymax>
		</bndbox>
	</object>
	<object>
		<name>table</name>
		<pose>Unspecified</pose>
		<truncated>0</truncated>
		<difficult>0</difficult>
		<bndbox>
			<xmin>506</xmin>
			<ymin>123</ymin>
			<xmax>565</xmax>
			<ymax>407</ymax>
		</bndbox>
	</object>
</annotation>
