<annotation>
	<folder>orignal-images</folder>
	<filename>img941.png</filename>
	<path>/Users/zhongjie/MyWorkspace/temp/orignal-images/img941.png</path>
	<source>
		<database>Unknown</database>
	</source>
	<size>
		<width>633</width>
		<height>805</height>
		<depth>3</depth>
	</size>
	<segmented>0</segmented>
	<object>
		<name>table</name>
		<pose>Unspecified</pose>
		<truncated>0</truncated>
		<difficult>0</difficult>
		<bndbox>
			<xmin>430</xmin>
			<ymin>118</ymin>
			<xmax>594</xmax>
			<ymax>317</ymax>
		</bndbox>
	</object>
</annotation>
